samgeo/__init__.py
samgeo/common.py
samgeo/custom_automatic_mask_generator.py
samgeo/fast_sam.py
samgeo/fer.py
samgeo/hq_sam.py
samgeo/samgeo.py
samgeo/samgeo2.py
samgeo/text_sam.py
samgeo/utmconv.py
segment_geospatial_uni-0.0.2.dist-info/licenses/LICENSE
segment_geospatial_uni-0.0.2.dist-info/METADATA
segment_geospatial_uni-0.0.2.dist-info/WHEEL
segment_geospatial_uni-0.0.2.dist-info/top_level.txt
segment_geospatial_uni-0.0.2.dist-info/RECORD
