Metadata-Version: 2.4
Name: segment-geospatial-uni
Version: 0.0.2
Summary: Meta AI' Segment Anything Model (SAM) for Geospatial Data.
Author-email: Qiusheng Wu <giswqs@gmail.com>
License: MIT license
Project-URL: Homepage, https://github.com/opengeos/segment-geospatial
Keywords: samgeo
Classifier: Development Status :: 2 - Pre-Alpha
Classifier: Intended Audience :: Developers
Classifier: License :: OSI Approved :: MIT License
Classifier: Natural Language :: English
Classifier: Programming Language :: Python :: 3
Classifier: Programming Language :: Python :: 3.10
Classifier: Programming Language :: Python :: 3.11
Classifier: Programming Language :: Python :: 3.12
Requires-Python: >=3.10
License-File: LICENSE
Requires-Dist: fiona
Requires-Dist: gdown
Requires-Dist: geopandas
Requires-Dist: huggingface_hub
Requires-Dist: ipympl
Requires-Dist: leafmap
Requires-Dist: localtileserver
Requires-Dist: matplotlib
Requires-Dist: opencv-python-headless
Requires-Dist: patool
Requires-Dist: pycocotools
Requires-Dist: pyproj
Requires-Dist: rasterio
Requires-Dist: rioxarray
Requires-Dist: sam-2-uni
Requires-Dist: scikit-image
Requires-Dist: scikit-learn
Requires-Dist: segment-anything-hq
Requires-Dist: segment-anything-py
Requires-Dist: timm
Requires-Dist: tqdm
Requires-Dist: xarray
Requires-Dist: xyzservices
Provides-Extra: all
Requires-Dist: groundingdino-py; extra == "all"
Dynamic: license-file
